<annotation>
    <folder>edited</folder>
    <filename>10.jpg</filename>
    <size>
        <width>4000</width>
        <height>2250</height>
        <depth>3</depth>
    </size>
    <segmented>0</segmented>
    <object>
        <name>PlasticBottle</name>
        <pose>Unspecified</pose>
        <truncated>0</truncated>
        <occluded>0</occluded>
        <difficult>0</difficult>
        <bndbox>
            <xmin>2640</xmin>
            <ymin>234</ymin>
            <xmax>2702</xmax>
            <ymax>336</ymax>
        </bndbox>
    </object>
    <object>
        <name>Plastic</name>
        <pose>Unspecified</pose>
        <truncated>0</truncated>
        <occluded>0</occluded>
        <difficult>0</difficult>
        <bndbox>
            <xmin>3948</xmin>
            <ymin>466</ymin>
            <xmax>4000</xmax>
            <ymax>575</ymax>
        </bndbox>
    </object>
    <object>
        <name>Plastic</name>
        <pose>Unspecified</pose>
        <truncated>0</truncated>
        <occluded>0</occluded>
        <difficult>0</difficult>
        <bndbox>
            <xmin>3720</xmin>
            <ymin>1183</ymin>
            <xmax>3810</xmax>
            <ymax>1257</ymax>
        </bndbox>
    </object>
    <object>
        <name>Plastic</name>
        <pose>Unspecified</pose>
        <truncated>0</truncated>
        <occluded>0</occluded>
        <difficult>0</difficult>
        <bndbox>
            <xmin>3634</xmin>
            <ymin>338</ymin>
            <xmax>3737</xmax>
            <ymax>424</ymax>
        </bndbox>
    </object>
    <object>
        <name>Plastic</name>
        <pose>Unspecified</pose>
        <truncated>0</truncated>
        <occluded>0</occluded>
        <difficult>0</difficult>
        <bndbox>
            <xmin>3693</xmin>
            <ymin>1254</ymin>
            <xmax>3741</xmax>
            <ymax>1305</ymax>
        </bndbox>
    </object>
    <object>
        <name>Plastic</name>
        <pose>Unspecified</pose>
        <truncated>0</truncated>
        <occluded>0</occluded>
        <difficult>0</difficult>
        <bndbox>
            <xmin>3116</xmin>
            <ymin>1992</ymin>
            <xmax>3218</xmax>
            <ymax>2107</ymax>
        </bndbox>
    </object>
    <object>
        <name>Plastic</name>
        <pose>Unspecified</pose>
        <truncated>0</truncated>
        <occluded>0</occluded>
        <difficult>0</difficult>
        <bndbox>
            <xmin>2027</xmin>
            <ymin>1378</ymin>
            <xmax>2090</xmax>
            <ymax>1441</ymax>
        </bndbox>
    </object>
    <object>
        <name>PlasticBottle</name>
        <pose>Unspecified</pose>
        <truncated>0</truncated>
        <occluded>0</occluded>
        <difficult>0</difficult>
        <bndbox>
            <xmin>2267</xmin>
            <ymin>1023</ymin>
            <xmax>2361</xmax>
            <ymax>1064</ymax>
        </bndbox>
    </object>
    <object>
        <name>Plastic</name>
        <pose>Unspecified</pose>
        <truncated>0</truncated>
        <occluded>0</occluded>
        <difficult>0</difficult>
        <bndbox>
            <xmin>2652</xmin>
            <ymin>448</ymin>
            <xmax>2708</xmax>
            <ymax>501</ymax>
        </bndbox>
    </object>
    <object>
        <name>PlasticBottle</name>
        <pose>Unspecified</pose>
        <truncated>0</truncated>
        <occluded>0</occluded>
        <difficult>0</difficult>
        <bndbox>
            <xmin>2640</xmin>
            <ymin>235</ymin>
            <xmax>2700</xmax>
            <ymax>338</ymax>
        </bndbox>
    </object>
    <object>
        <name>Plastic</name>
        <pose>Unspecified</pose>
        <truncated>0</truncated>
        <occluded>0</occluded>
        <difficult>0</difficult>
        <bndbox>
            <xmin>1903</xmin>
            <ymin>1</ymin>
            <xmax>2008</xmax>
            <ymax>74</ymax>
        </bndbox>
    </object>
</annotation>