<annotation>
    <folder>5m</folder>
    <filename>DJI_0173.JPG</filename>
    <size>
        <width>4000</width>
        <height>2250</height>
        <depth>3</depth>
    </size>
    <segmented>0</segmented>
    <object>
        <name>PlasticBottle</name>
        <pose>Unspecified</pose>
        <truncated>0</truncated>
        <occluded>0</occluded>
        <difficult>0</difficult>
        <bndbox>
            <xmin>2738</xmin>
            <ymin>982</ymin>
            <xmax>2794</xmax>
            <ymax>1088</ymax>
        </bndbox>
    </object>
    <object>
        <name>PlasticBottle</name>
        <pose>Unspecified</pose>
        <truncated>0</truncated>
        <occluded>0</occluded>
        <difficult>0</difficult>
        <bndbox>
            <xmin>2599</xmin>
            <ymin>1996</ymin>
            <xmax>2643</xmax>
            <ymax>2086</ymax>
        </bndbox>
    </object>
    <object>
        <name>PlasticBottle</name>
        <pose>Unspecified</pose>
        <truncated>0</truncated>
        <occluded>0</occluded>
        <difficult>0</difficult>
        <bndbox>
            <xmin>1576</xmin>
            <ymin>2126</ymin>
            <xmax>1668</xmax>
            <ymax>2163</ymax>
        </bndbox>
    </object>
    <object>
        <name>PlasticBottle</name>
        <pose>Unspecified</pose>
        <truncated>0</truncated>
        <occluded>0</occluded>
        <difficult>0</difficult>
        <bndbox>
            <xmin>2181</xmin>
            <ymin>1503</ymin>
            <xmax>2275</xmax>
            <ymax>1589</ymax>
        </bndbox>
    </object>
    <object>
        <name>Plastic</name>
        <pose>Unspecified</pose>
        <truncated>0</truncated>
        <occluded>0</occluded>
        <difficult>0</difficult>
        <bndbox>
            <xmin>1742</xmin>
            <ymin>1422</ymin>
            <xmax>1809</xmax>
            <ymax>1514</ymax>
        </bndbox>
    </object>
    <object>
        <name>Plastic</name>
        <pose>Unspecified</pose>
        <truncated>0</truncated>
        <occluded>0</occluded>
        <difficult>0</difficult>
        <bndbox>
            <xmin>1601</xmin>
            <ymin>1066</ymin>
            <xmax>1683</xmax>
            <ymax>1157</ymax>
        </bndbox>
    </object>
</annotation>