<annotation>
    <folder>New folder</folder>
    <filename>DJI_0263.JPG</filename>
    <size>
        <width>4000</width>
        <height>2250</height>
        <depth>3</depth>
    </size>
    <segmented>0</segmented>
    <object>
        <name>PlasticBottle</name>
        <pose>Unspecified</pose>
        <truncated>0</truncated>
        <occluded>0</occluded>
        <difficult>0</difficult>
        <bndbox>
            <xmin>1517</xmin>
            <ymin>947</ymin>
            <xmax>1547</xmax>
            <ymax>983</ymax>
        </bndbox>
    </object>
    <object>
        <name>Can</name>
        <pose>Unspecified</pose>
        <truncated>0</truncated>
        <occluded>0</occluded>
        <difficult>0</difficult>
        <bndbox>
            <xmin>1842</xmin>
            <ymin>864</ymin>
            <xmax>1873</xmax>
            <ymax>894</ymax>
        </bndbox>
    </object>
    <object>
        <name>Plastic</name>
        <pose>Unspecified</pose>
        <truncated>0</truncated>
        <occluded>0</occluded>
        <difficult>0</difficult>
        <bndbox>
            <xmin>1662</xmin>
            <ymin>794</ymin>
            <xmax>1692</xmax>
            <ymax>843</ymax>
        </bndbox>
    </object>
    <object>
        <name>Plastic</name>
        <pose>Unspecified</pose>
        <truncated>0</truncated>
        <occluded>0</occluded>
        <difficult>0</difficult>
        <bndbox>
            <xmin>1665</xmin>
            <ymin>852</ymin>
            <xmax>1690</xmax>
            <ymax>872</ymax>
        </bndbox>
    </object>
    <object>
        <name>Plastic</name>
        <pose>Unspecified</pose>
        <truncated>0</truncated>
        <occluded>0</occluded>
        <difficult>0</difficult>
        <bndbox>
            <xmin>1580</xmin>
            <ymin>831</ymin>
            <xmax>1616</xmax>
            <ymax>876</ymax>
        </bndbox>
    </object>
    <object>
        <name>Can</name>
        <pose>Unspecified</pose>
        <truncated>0</truncated>
        <occluded>0</occluded>
        <difficult>0</difficult>
        <bndbox>
            <xmin>1472</xmin>
            <ymin>999</ymin>
            <xmax>1503</xmax>
            <ymax>1020</ymax>
        </bndbox>
    </object>
    <object>
        <name>PlasticBottle</name>
        <pose>Unspecified</pose>
        <truncated>0</truncated>
        <occluded>0</occluded>
        <difficult>0</difficult>
        <bndbox>
            <xmin>1447</xmin>
            <ymin>978</ymin>
            <xmax>1504</xmax>
            <ymax>996</ymax>
        </bndbox>
    </object>
    <object>
        <name>Can</name>
        <pose>Unspecified</pose>
        <truncated>0</truncated>
        <occluded>0</occluded>
        <difficult>0</difficult>
        <bndbox>
            <xmin>1436</xmin>
            <ymin>917</ymin>
            <xmax>1477</xmax>
            <ymax>948</ymax>
        </bndbox>
    </object>
    <object>
        <name>Can</name>
        <pose>Unspecified</pose>
        <truncated>0</truncated>
        <occluded>0</occluded>
        <difficult>0</difficult>
        <bndbox>
            <xmin>1414</xmin>
            <ymin>780</ymin>
            <xmax>1440</xmax>
            <ymax>830</ymax>
        </bndbox>
    </object>
    <object>
        <name>Can</name>
        <pose>Unspecified</pose>
        <truncated>0</truncated>
        <occluded>0</occluded>
        <difficult>0</difficult>
        <bndbox>
            <xmin>1701</xmin>
            <ymin>741</ymin>
            <xmax>1728</xmax>
            <ymax>775</ymax>
        </bndbox>
    </object>
</annotation>